{
    "name": "GiftcardType",
    "fields": [
        {
            "fieldName": "name",
            "fieldType": "String",
            "fieldValidateRules": [
                "required"
            ]
        },
        {
            "fieldName": "storeId",
            "fieldType": "Integer",
            "fieldValidateRules": [
                "required"
            ]
        }
    ],
    "relationships": [
        {
            "relationshipName": "store",
            "otherEntityName": "store",
            "relationshipType": "many-to-one",
            "otherEntityField": "id"
        },
        {
            "relationshipType": "one-to-many",
            "relationshipName": "giftcardTypeId",
            "otherEntityName": "giftcard",
            "otherEntityRelationshipName": "giftcardType"
        }
    ],
    "changelogDate": "20181201203603",
    "entityTableName": "giftcard_type",
    "dto": "no",
    "pagination": "infinite-scroll",
    "service": "no",
    "jpaMetamodelFiltering": false,
    "fluentMethods": true,
    "clientRootFolder": "",
    "applications": "*"
}